tychos/__init__.py
tychos/cli.py
tychos/config.py
tychos/vector.py
tychos/vector_data_store.py
tychos/helpers/__init__.py
tychos/helpers/validation_checks.py
tychos-0.1.2.dist-info/LICENSE
tychos-0.1.2.dist-info/METADATA
tychos-0.1.2.dist-info/WHEEL
tychos-0.1.2.dist-info/entry_points.txt
tychos-0.1.2.dist-info/top_level.txt
tychos-0.1.2.dist-info/RECORD
