Metadata-Version: 2.1
Name: tychos
Version: 0.1.2
Summary: Python client library for the Tychos API.
Requires-Python: >=3.6
License-File: LICENSE
Requires-Dist: requests
